exam_avezorgen
