Metadata-Version: 1.2
Name: exam-avezorgen
Version: 0.0.4
Summary: A few short programs for exam
Home-page: UNKNOWN
Author: AveZorgen
License: UNKNOWN
Platform: UNKNOWN
Classifier: Programming Language :: Python :: 3.8
Classifier: License :: OSI Approved :: MIT License
Classifier: Operating System :: OS Independent
Requires-Python: >=3.6
